{
    "description": "",
    "tags": [],
    "size": {
        "height": 600,
        "width": 800
    },
    "objects": [
        {
            "id": 6276098,
            "classId": 8683,
            "description": "",
            "geometryType": "rectangle",
            "labelerLogin": "iw@datasetninja.com",
            "createdAt": "2023-06-13T15:45:18.468Z",
            "updatedAt": "2023-06-13T15:45:18.468Z",
            "tags": [],
            "classTitle": "strawberry",
            "points": {
                "exterior": [
                    [
                        132,
                        286
                    ],
                    [
                        225,
                        390
                    ]
                ],
                "interior": []
            }
        },
        {
            "id": 6276097,
            "classId": 8683,
            "description": "",
            "geometryType": "rectangle",
            "labelerLogin": "iw@datasetninja.com",
            "createdAt": "2023-06-13T15:45:18.468Z",
            "updatedAt": "2023-06-13T15:45:18.468Z",
            "tags": [],
            "classTitle": "strawberry",
            "points": {
                "exterior": [
                    [
                        180,
                        374
                    ],
                    [
                        268,
                        457
                    ]
                ],
                "interior": []
            }
        },
        {
            "id": 6276096,
            "classId": 8683,
            "description": "",
            "geometryType": "rectangle",
            "labelerLogin": "iw@datasetninja.com",
            "createdAt": "2023-06-13T15:45:18.467Z",
            "updatedAt": "2023-06-13T15:45:18.467Z",
            "tags": [],
            "classTitle": "strawberry",
            "points": {
                "exterior": [
                    [
                        273,
                        301
                    ],
                    [
                        349,
                        420
                    ]
                ],
                "interior": []
            }
        },
        {
            "id": 6276095,
            "classId": 8683,
            "description": "",
            "geometryType": "rectangle",
            "labelerLogin": "iw@datasetninja.com",
            "createdAt": "2023-06-13T15:45:18.467Z",
            "updatedAt": "2023-06-13T15:45:18.467Z",
            "tags": [],
            "classTitle": "strawberry",
            "points": {
                "exterior": [
                    [
                        438,
                        287
                    ],
                    [
                        498,
                        341
                    ]
                ],
                "interior": []
            }
        },
        {
            "id": 6276094,
            "classId": 8683,
            "description": "",
            "geometryType": "rectangle",
            "labelerLogin": "iw@datasetninja.com",
            "createdAt": "2023-06-13T15:45:18.467Z",
            "updatedAt": "2023-06-13T15:45:18.467Z",
            "tags": [],
            "classTitle": "strawberry",
            "points": {
                "exterior": [
                    [
                        493,
                        323
                    ],
                    [
                        543,
                        404
                    ]
                ],
                "interior": []
            }
        },
        {
            "id": 6276093,
            "classId": 8683,
            "description": "",
            "geometryType": "rectangle",
            "labelerLogin": "iw@datasetninja.com",
            "createdAt": "2023-06-13T15:45:18.467Z",
            "updatedAt": "2023-06-13T15:45:18.467Z",
            "tags": [],
            "classTitle": "strawberry",
            "points": {
                "exterior": [
                    [
                        597,
                        296
                    ],
                    [
                        683,
                        367
                    ]
                ],
                "interior": []
            }
        },
        {
            "id": 6276092,
            "classId": 8683,
            "description": "",
            "geometryType": "rectangle",
            "labelerLogin": "iw@datasetninja.com",
            "createdAt": "2023-06-13T15:45:18.466Z",
            "updatedAt": "2023-06-13T15:45:18.466Z",
            "tags": [],
            "classTitle": "strawberry",
            "points": {
                "exterior": [
                    [
                        325,
                        213
                    ],
                    [
                        391,
                        272
                    ]
                ],
                "interior": []
            }
        },
        {
            "id": 6276091,
            "classId": 8683,
            "description": "",
            "geometryType": "rectangle",
            "labelerLogin": "iw@datasetninja.com",
            "createdAt": "2023-06-13T15:45:18.465Z",
            "updatedAt": "2023-06-13T15:45:18.465Z",
            "tags": [],
            "classTitle": "strawberry",
            "points": {
                "exterior": [
                    [
                        263,
                        213
                    ],
                    [
                        331,
                        287
                    ]
                ],
                "interior": []
            }
        },
        {
            "id": 6276090,
            "classId": 8683,
            "description": "",
            "geometryType": "rectangle",
            "labelerLogin": "iw@datasetninja.com",
            "createdAt": "2023-06-13T15:45:18.465Z",
            "updatedAt": "2023-06-13T15:45:18.465Z",
            "tags": [],
            "classTitle": "strawberry",
            "points": {
                "exterior": [
                    [
                        254,
                        149
                    ],
                    [
                        344,
                        212
                    ]
                ],
                "interior": []
            }
        },
        {
            "id": 6276089,
            "classId": 8683,
            "description": "",
            "geometryType": "rectangle",
            "labelerLogin": "iw@datasetninja.com",
            "createdAt": "2023-06-13T15:45:18.465Z",
            "updatedAt": "2023-06-13T15:45:18.465Z",
            "tags": [],
            "classTitle": "strawberry",
            "points": {
                "exterior": [
                    [
                        112,
                        232
                    ],
                    [
                        196,
                        305
                    ]
                ],
                "interior": []
            }
        }
    ]
}