{
    "description": "",
    "tags": [],
    "size": {
        "height": 1365,
        "width": 2048
    },
    "objects": [
        {
            "id": 6298063,
            "classId": 8679,
            "description": "",
            "geometryType": "rectangle",
            "labelerLogin": "iw@datasetninja.com",
            "createdAt": "2023-06-13T15:46:05.364Z",
            "updatedAt": "2023-06-13T15:46:05.364Z",
            "tags": [],
            "classTitle": "cherry",
            "points": {
                "exterior": [
                    [
                        1351,
                        848
                    ],
                    [
                        1663,
                        1170
                    ]
                ],
                "interior": []
            }
        },
        {
            "id": 6298062,
            "classId": 8679,
            "description": "",
            "geometryType": "rectangle",
            "labelerLogin": "iw@datasetninja.com",
            "createdAt": "2023-06-13T15:46:05.364Z",
            "updatedAt": "2023-06-13T15:46:05.364Z",
            "tags": [],
            "classTitle": "cherry",
            "points": {
                "exterior": [
                    [
                        1908,
                        860
                    ],
                    [
                        2047,
                        1192
                    ]
                ],
                "interior": []
            }
        },
        {
            "id": 6298061,
            "classId": 8679,
            "description": "",
            "geometryType": "rectangle",
            "labelerLogin": "iw@datasetninja.com",
            "createdAt": "2023-06-13T15:46:05.363Z",
            "updatedAt": "2023-06-13T15:46:05.363Z",
            "tags": [],
            "classTitle": "cherry",
            "points": {
                "exterior": [
                    [
                        993,
                        975
                    ],
                    [
                        1257,
                        1218
                    ]
                ],
                "interior": []
            }
        },
        {
            "id": 6298060,
            "classId": 8679,
            "description": "",
            "geometryType": "rectangle",
            "labelerLogin": "iw@datasetninja.com",
            "createdAt": "2023-06-13T15:46:05.363Z",
            "updatedAt": "2023-06-13T15:46:05.363Z",
            "tags": [],
            "classTitle": "cherry",
            "points": {
                "exterior": [
                    [
                        1231,
                        990
                    ],
                    [
                        1465,
                        1262
                    ]
                ],
                "interior": []
            }
        },
        {
            "id": 6298059,
            "classId": 8679,
            "description": "",
            "geometryType": "rectangle",
            "labelerLogin": "iw@datasetninja.com",
            "createdAt": "2023-06-13T15:46:05.363Z",
            "updatedAt": "2023-06-13T15:46:05.363Z",
            "tags": [],
            "classTitle": "cherry",
            "points": {
                "exterior": [
                    [
                        1458,
                        1063
                    ],
                    [
                        1746,
                        1312
                    ]
                ],
                "interior": []
            }
        },
        {
            "id": 6298058,
            "classId": 8679,
            "description": "",
            "geometryType": "rectangle",
            "labelerLogin": "iw@datasetninja.com",
            "createdAt": "2023-06-13T15:46:05.363Z",
            "updatedAt": "2023-06-13T15:46:05.363Z",
            "tags": [],
            "classTitle": "cherry",
            "points": {
                "exterior": [
                    [
                        1061,
                        730
                    ],
                    [
                        1354,
                        1025
                    ]
                ],
                "interior": []
            }
        }
    ]
}