{
    "description": "",
    "tags": [],
    "size": {
        "height": 500,
        "width": 500
    },
    "objects": [
        {
            "id": 6314044,
            "classId": 8679,
            "description": "",
            "geometryType": "rectangle",
            "labelerLogin": "iw@datasetninja.com",
            "createdAt": "2023-06-13T15:46:36.514Z",
            "updatedAt": "2023-06-13T15:46:36.514Z",
            "tags": [],
            "classTitle": "cherry",
            "points": {
                "exterior": [
                    [
                        284,
                        104
                    ],
                    [
                        365,
                        176
                    ]
                ],
                "interior": []
            }
        },
        {
            "id": 6314043,
            "classId": 8679,
            "description": "",
            "geometryType": "rectangle",
            "labelerLogin": "iw@datasetninja.com",
            "createdAt": "2023-06-13T15:46:36.513Z",
            "updatedAt": "2023-06-13T15:46:36.513Z",
            "tags": [],
            "classTitle": "cherry",
            "points": {
                "exterior": [
                    [
                        398,
                        170
                    ],
                    [
                        470,
                        268
                    ]
                ],
                "interior": []
            }
        },
        {
            "id": 6314042,
            "classId": 8679,
            "description": "",
            "geometryType": "rectangle",
            "labelerLogin": "iw@datasetninja.com",
            "createdAt": "2023-06-13T15:46:36.513Z",
            "updatedAt": "2023-06-13T15:46:36.513Z",
            "tags": [],
            "classTitle": "cherry",
            "points": {
                "exterior": [
                    [
                        336,
                        193
                    ],
                    [
                        424,
                        282
                    ]
                ],
                "interior": []
            }
        },
        {
            "id": 6314041,
            "classId": 8679,
            "description": "",
            "geometryType": "rectangle",
            "labelerLogin": "iw@datasetninja.com",
            "createdAt": "2023-06-13T15:46:36.513Z",
            "updatedAt": "2023-06-13T15:46:36.513Z",
            "tags": [],
            "classTitle": "cherry",
            "points": {
                "exterior": [
                    [
                        206,
                        200
                    ],
                    [
                        313,
                        300
                    ]
                ],
                "interior": []
            }
        },
        {
            "id": 6314040,
            "classId": 8679,
            "description": "",
            "geometryType": "rectangle",
            "labelerLogin": "iw@datasetninja.com",
            "createdAt": "2023-06-13T15:46:36.513Z",
            "updatedAt": "2023-06-13T15:46:36.513Z",
            "tags": [],
            "classTitle": "cherry",
            "points": {
                "exterior": [
                    [
                        105,
                        208
                    ],
                    [
                        205,
                        311
                    ]
                ],
                "interior": []
            }
        },
        {
            "id": 6314039,
            "classId": 8679,
            "description": "",
            "geometryType": "rectangle",
            "labelerLogin": "iw@datasetninja.com",
            "createdAt": "2023-06-13T15:46:36.513Z",
            "updatedAt": "2023-06-13T15:46:36.513Z",
            "tags": [],
            "classTitle": "cherry",
            "points": {
                "exterior": [
                    [
                        315,
                        212
                    ],
                    [
                        410,
                        319
                    ]
                ],
                "interior": []
            }
        },
        {
            "id": 6314038,
            "classId": 8679,
            "description": "",
            "geometryType": "rectangle",
            "labelerLogin": "iw@datasetninja.com",
            "createdAt": "2023-06-13T15:46:36.513Z",
            "updatedAt": "2023-06-13T15:46:36.513Z",
            "tags": [],
            "classTitle": "cherry",
            "points": {
                "exterior": [
                    [
                        45,
                        239
                    ],
                    [
                        124,
                        328
                    ]
                ],
                "interior": []
            }
        },
        {
            "id": 6314037,
            "classId": 8679,
            "description": "",
            "geometryType": "rectangle",
            "labelerLogin": "iw@datasetninja.com",
            "createdAt": "2023-06-13T15:46:36.513Z",
            "updatedAt": "2023-06-13T15:46:36.513Z",
            "tags": [],
            "classTitle": "cherry",
            "points": {
                "exterior": [
                    [
                        256,
                        237
                    ],
                    [
                        354,
                        333
                    ]
                ],
                "interior": []
            }
        },
        {
            "id": 6314036,
            "classId": 8679,
            "description": "",
            "geometryType": "rectangle",
            "labelerLogin": "iw@datasetninja.com",
            "createdAt": "2023-06-13T15:46:36.513Z",
            "updatedAt": "2023-06-13T15:46:36.513Z",
            "tags": [],
            "classTitle": "cherry",
            "points": {
                "exterior": [
                    [
                        234,
                        291
                    ],
                    [
                        323,
                        355
                    ]
                ],
                "interior": []
            }
        },
        {
            "id": 6314035,
            "classId": 8679,
            "description": "",
            "geometryType": "rectangle",
            "labelerLogin": "iw@datasetninja.com",
            "createdAt": "2023-06-13T15:46:36.512Z",
            "updatedAt": "2023-06-13T15:46:36.512Z",
            "tags": [],
            "classTitle": "cherry",
            "points": {
                "exterior": [
                    [
                        85,
                        299
                    ],
                    [
                        181,
                        384
                    ]
                ],
                "interior": []
            }
        },
        {
            "id": 6314034,
            "classId": 8679,
            "description": "",
            "geometryType": "rectangle",
            "labelerLogin": "iw@datasetninja.com",
            "createdAt": "2023-06-13T15:46:36.512Z",
            "updatedAt": "2023-06-13T15:46:36.512Z",
            "tags": [],
            "classTitle": "cherry",
            "points": {
                "exterior": [
                    [
                        208,
                        310
                    ],
                    [
                        281,
                        380
                    ]
                ],
                "interior": []
            }
        },
        {
            "id": 6314033,
            "classId": 8679,
            "description": "",
            "geometryType": "rectangle",
            "labelerLogin": "iw@datasetninja.com",
            "createdAt": "2023-06-13T15:46:36.512Z",
            "updatedAt": "2023-06-13T15:46:36.512Z",
            "tags": [],
            "classTitle": "cherry",
            "points": {
                "exterior": [
                    [
                        91,
                        364
                    ],
                    [
                        168,
                        402
                    ]
                ],
                "interior": []
            }
        },
        {
            "id": 6314032,
            "classId": 8679,
            "description": "",
            "geometryType": "rectangle",
            "labelerLogin": "iw@datasetninja.com",
            "createdAt": "2023-06-13T15:46:36.512Z",
            "updatedAt": "2023-06-13T15:46:36.512Z",
            "tags": [],
            "classTitle": "cherry",
            "points": {
                "exterior": [
                    [
                        451,
                        351
                    ],
                    [
                        499,
                        420
                    ]
                ],
                "interior": []
            }
        },
        {
            "id": 6314031,
            "classId": 8679,
            "description": "",
            "geometryType": "rectangle",
            "labelerLogin": "iw@datasetninja.com",
            "createdAt": "2023-06-13T15:46:36.511Z",
            "updatedAt": "2023-06-13T15:46:36.511Z",
            "tags": [],
            "classTitle": "cherry",
            "points": {
                "exterior": [
                    [
                        242,
                        395
                    ],
                    [
                        326,
                        479
                    ]
                ],
                "interior": []
            }
        },
        {
            "id": 6314030,
            "classId": 8679,
            "description": "",
            "geometryType": "rectangle",
            "labelerLogin": "iw@datasetninja.com",
            "createdAt": "2023-06-13T15:46:36.511Z",
            "updatedAt": "2023-06-13T15:46:36.511Z",
            "tags": [],
            "classTitle": "cherry",
            "points": {
                "exterior": [
                    [
                        300,
                        425
                    ],
                    [
                        372,
                        497
                    ]
                ],
                "interior": []
            }
        },
        {
            "id": 6314029,
            "classId": 8679,
            "description": "",
            "geometryType": "rectangle",
            "labelerLogin": "iw@datasetninja.com",
            "createdAt": "2023-06-13T15:46:36.511Z",
            "updatedAt": "2023-06-13T15:46:36.511Z",
            "tags": [],
            "classTitle": "cherry",
            "points": {
                "exterior": [
                    [
                        234,
                        441
                    ],
                    [
                        304,
                        499
                    ]
                ],
                "interior": []
            }
        },
        {
            "id": 6314028,
            "classId": 8679,
            "description": "",
            "geometryType": "rectangle",
            "labelerLogin": "iw@datasetninja.com",
            "createdAt": "2023-06-13T15:46:36.511Z",
            "updatedAt": "2023-06-13T15:46:36.511Z",
            "tags": [],
            "classTitle": "cherry",
            "points": {
                "exterior": [
                    [
                        38,
                        0
                    ],
                    [
                        139,
                        98
                    ]
                ],
                "interior": []
            }
        },
        {
            "id": 6314027,
            "classId": 8679,
            "description": "",
            "geometryType": "rectangle",
            "labelerLogin": "iw@datasetninja.com",
            "createdAt": "2023-06-13T15:46:36.511Z",
            "updatedAt": "2023-06-13T15:46:36.511Z",
            "tags": [],
            "classTitle": "cherry",
            "points": {
                "exterior": [
                    [
                        38,
                        59
                    ],
                    [
                        139,
                        117
                    ]
                ],
                "interior": []
            }
        }
    ]
}